Metadata-Version: 2.1
Name: revChatGPT-ucafe
Version: 2.5.0
Summary: ChatGPT is a reverse engineering of OpenAI's ChatGPT API
Home-page: https://github.com/acheong08/ChatGPT
Author: Antonio Cheong
Author-email: acheong@student.dalat.org
License: GNU General Public License v2.0
Platform: UNKNOWN
Provides-Extra: unofficial
License-File: LICENSE
